{
  "PLACEHOLDER": {
    "in_use_in": []
  },
  "DEMO2": {
    "in_use_in": []
  },
  "DEBUG_TEXT": {
    "in_use_in": []
  },
  "MAP_MKS": {
    "in_use_in": []
  },
  "TEST": {
    "in_use_in": []
  },
  "MAP_DRIFTWAY": {
    "in_use_in": [
      "Map"
    ]
  },
  "MAP_RBR": {
    "in_use_in": []
  },
  "CHARACTER_KNUCKLES": {
    "in_use_in": [
      "Character"
    ]
  },
  "CHARACTER_MARIO": {
    "in_use_in": []
  },
  "KART_STANDARD": {
    "in_use_in": []
  },
  "KART_MK_WII": {
    "in_use_in": [
      "Vehicle"
    ]
  },
  "KART_MK8": {
    "in_use_in": [
      "Vehicle"
    ]
  },
  "MAP_SELECT": {
    "in_use_in": []
  },
  "CHARACTER_SELECT": {
    "in_use_in": []
  },
  "VEHICLE_SELECT": {
    "in_use_in": []
  },
  "DEMO_CUP": {
    "in_use_in": [
      "Cup"
    ]
  },
  "CUP_SELECT": {
    "in_use_in": []
  },
  "MAP_YOSHI_CIRCUIT": {
    "in_use_in": [
      "Map"
    ]
  },
  "MAP_MEADOWS": {
    "in_use_in": [
      "Map"
    ]
  },
  "MAP_SUBWAY": {
    "in_use_in": [
      "Map"
    ]
  },
  "TEST MAP": {
    "in_use_in": [
      "Map"
    ]
  },
  "MUTE CITY": {
    "in_use_in": [
      "Map"
    ]
  },
  "CHARACTER_BOWSER": {
    "in_use_in": [
      "Character"
    ]
  },
  "CHARACTER_WALUIGI": {
    "in_use_in": [
      "Character"
    ]
  },
  "CHARACTER_ROSALINA": {
    "in_use_in": [
      "Character"
    ]
  },
  "CHARACTER_BABY_MARIO": {
    "in_use_in": [
      "Character"
    ]
  },
  "CUP": {
    "in_use_in": []
  },
  "RACE": {
    "in_use_in": []
  },
  "CHARACTER_YOSHI": {
    "in_use_in": [
      "Character"
    ]
  },
  "EXIT": {
    "in_use_in": []
  },
  "MAIN_SELECT": {
    "in_use_in": []
  }
}